pybarrnap/__init__.py
pybarrnap/__main__.py
pybarrnap/barrnap.py
pybarrnap/config.py
pybarrnap/logger.py
pybarrnap/record.py
pybarrnap/result.py
pybarrnap/utils.py
pybarrnap/db/LICENSE.Barrnap
pybarrnap/db/LICENSE.Rfam
pybarrnap/db/cm/all.cm.i1f
pybarrnap/db/cm/all.cm.i1i
pybarrnap/db/cm/all.cm.i1m
pybarrnap/db/cm/all.cm.i1p
pybarrnap/db/cm/arc.cm.i1f
pybarrnap/db/cm/arc.cm.i1i
pybarrnap/db/cm/arc.cm.i1m
pybarrnap/db/cm/arc.cm.i1p
pybarrnap/db/cm/bac.cm.i1f
pybarrnap/db/cm/bac.cm.i1i
pybarrnap/db/cm/bac.cm.i1m
pybarrnap/db/cm/bac.cm.i1p
pybarrnap/db/cm/euk.cm.i1f
pybarrnap/db/cm/euk.cm.i1i
pybarrnap/db/cm/euk.cm.i1m
pybarrnap/db/cm/euk.cm.i1p
pybarrnap/db/hmm/arc.hmm
pybarrnap/db/hmm/bac.hmm
pybarrnap/db/hmm/euk.hmm
pybarrnap/example_data/archaea.fna
pybarrnap/example_data/bacteria.fna
pybarrnap/example_data/dupid.fna
pybarrnap/example_data/empty.fna
pybarrnap/example_data/fungus.fna
pybarrnap/example_data/minimum.fna
pybarrnap/example_data/minimum.fna.gz
pybarrnap/example_data/nohits.fna
pybarrnap/example_data/null.fna
pybarrnap/example_data/protein.fna
pybarrnap/scripts/__init__.py
pybarrnap/scripts/pybarrnap.py
pybarrnap-0.5.1.dist-info/METADATA
pybarrnap-0.5.1.dist-info/WHEEL
pybarrnap-0.5.1.dist-info/entry_points.txt
pybarrnap-0.5.1.dist-info/licenses/LICENSE
pybarrnap-0.5.1.dist-info/RECORD
