Metadata-Version: 2.3
Name: pybarrnap
Version: 0.5.1
Summary: Python implementation of barrnap (Bacterial ribosomal RNA predictor)
Project-URL: homepage, https://github.com/moshi4/pybarrnap/
Project-URL: repository, https://github.com/moshi4/pybarrnap/
Author: moshi4
License: GPL-3.0-only
Keywords: bioinformatics
Classifier: Intended Audience :: Science/Research
Classifier: Topic :: Scientific/Engineering :: Bio-Informatics
Requires-Python: >=3.9
Requires-Dist: biopython>=1.80
Requires-Dist: pyhmmer>=0.11.0
